filtragemACrm
