Metadata-Version: 1.0
Name: filtragemACrm
Version: 0.0.5
Summary: Métodos de filtragem de imagem repetida e com blur
Home-page: https://github.com/alancaio/filtragemACrm
Author: Alan Caio Rodrigues Marques
Author-email: alancaiorm@gmail.com
License: MIT License
Keywords: filtragem imagens duplicadas
Platform: UNKNOWN
